setup.py
HATT/__init__.py
HATT/get_pr_gids_plots.py
HATT/get_pr_nyt10_plots.py
HATT/run.py
HATT/setup.py
HATT/utils.py
HATT/baselines_pr/__init__.py
HATT/benchmark/__init__.py
HATT/hatt/__init__.py
HATT/hatt/data_loader/__init__.py
HATT/hatt/data_loader/data_loader.py
HATT/hatt/encoder/__init__.py
HATT/hatt/encoder/bert_encoder.py
HATT/hatt/framework/__init__.py
HATT/hatt/framework/bag_re.py
HATT/hatt/framework/utils.py
HATT/hatt/selector/__init__.py
HATT/hatt/selector/bag_attention.py
dsre1.egg-info/PKG-INFO
dsre1.egg-info/SOURCES.txt
dsre1.egg-info/dependency_links.txt
dsre1.egg-info/top_level.txt