Metadata-Version: 1.0
Name: dsre1
Version: 0.1
Summary: dsre1 package
Home-page: https://github.com/JarvisFree/PyUtilityTool
Author: cml
Author-email: 1527449673@qq.com
License: UNKNOWN
Platform: UNKNOWN
